{
  "id": "5c78bf4f-ffc6-430c-8b37-ae05e3156f21",
  "revision": 0,
  "last_node_id": 7,
  "last_link_id": 7,
  "nodes": [
    {
      "id": 4,
      "type": "Apply Whisper",
      "pos": [
        -444.7578125,
        223.07493591308594
      ],
      "size": [
        230.76168823242188,
        98
      ],
      "flags": {},
      "order": 1,
      "mode": 0,
      "inputs": [
        {
          "name": "audio",
          "type": "AUDIO",
          "link": 3
        }
      ],
      "outputs": [
        {
          "name": "text",
          "type": "STRING",
          "links": [
            4,
            5
          ]
        },
        {
          "name": "segments_alignment",
          "type": "whisper_alignment",
          "links": null
        },
        {
          "name": "words_alignment",
          "type": "whisper_alignment",
          "links": null
        }
      ],
      "properties": {
        "cnr_id": "ComfyUI-Whisper",
        "ver": "edd1a485acf5e1e14835fdf8c4af982c0eaf115f",
        "Node name for S&R": "Apply Whisper"
      },
      "widgets_values": [
        "base"
      ]
    },
    {
      "id": 5,
      "type": "Show any [Crystools]",
      "pos": [
        -493.1012878417969,
        375.4639587402344
      ],
      "size": [
        312.6667175292969,
        236.6438446044922
      ],
      "flags": {},
      "order": 3,
      "mode": 0,
      "inputs": [
        {
          "name": "any_value",
          "shape": 7,
          "type": "*",
          "link": 4
        }
      ],
      "outputs": [],
      "properties": {
        "cnr_id": "ComfyUI-Crystools",
        "ver": "0820a7560bcc405ef6d0a7c5c53a83cc02ae7db2",
        "Node name for S&R": "Show any [Crystools]"
      }
    },
    {
      "id": 1,
      "type": "F5TTSAudioInputs",
      "pos": [
        -172.915283203125,
        148.6692657470703
      ],
      "size": [
        400,
        256
      ],
      "flags": {},
      "order": 4,
      "mode": 0,
      "inputs": [
        {
          "name": "sample_audio",
          "type": "AUDIO",
          "link": 1
        },
        {
          "name": "sample_text",
          "type": "STRING",
          "widget": {
            "name": "sample_text"
          },
          "link": 5
        }
      ],
      "outputs": [
        {
          "name": "AUDIO",
          "type": "AUDIO",
          "links": [
            6
          ]
        }
      ],
      "properties": {
        "cnr_id": "comfyui-f5-tts",
        "ver": "712bdfbd9185bd66ef49a160381cdd4f22e039d1",
        "Node name for S&R": "F5TTSAudioInputs"
      },
      "widgets_values": [
        "Text of sample_audio",
        "This is what I want to say",
        1,
        "randomize",
        "F5",
        "auto",
        1,
        "F5TTS_v1_Base"
      ]
    },
    {
      "id": 6,
      "type": "SaveAudio",
      "pos": [
        254.61178588867188,
        152.83851623535156
      ],
      "size": [
        315,
        112
      ],
      "flags": {},
      "order": 5,
      "mode": 0,
      "inputs": [
        {
          "name": "audio",
          "type": "AUDIO",
          "link": 6
        }
      ],
      "outputs": [],
      "properties": {
        "cnr_id": "comfy-core",
        "ver": "0.3.28",
        "Node name for S&R": "SaveAudio"
      },
      "widgets_values": [
        "audio/ComfyUI",
        ""
      ]
    },
    {
      "id": 2,
      "type": "VHS_LoadAudioUpload",
      "pos": [
        -720.8380737304688,
        145.10012817382812
      ],
      "size": [
        243.818359375,
        130
      ],
      "flags": {},
      "order": 0,
      "mode": 0,
      "inputs": [],
      "outputs": [
        {
          "name": "audio",
          "type": "AUDIO",
          "links": [
            1,
            3,
            7
          ]
        }
      ],
      "properties": {
        "cnr_id": "comfyui-videohelpersuite",
        "ver": "df55f01d1df2f7bf5cc772294bc2e6d8bab22d66",
        "Node name for S&R": "VHS_LoadAudioUpload"
      },
      "widgets_values": {
        "audio": "voice.mp3",
        "start_time": 0,
        "duration": 15.000000000000004,
        "choose audio to upload": "image"
      }
    },
    {
      "id": 7,
      "type": "PreviewAudio",
      "pos": [
        -836.2974243164062,
        333.6549377441406
      ],
      "size": [
        315,
        88
      ],
      "flags": {},
      "order": 2,
      "mode": 0,
      "inputs": [
        {
          "name": "audio",
          "type": "AUDIO",
          "link": 7
        }
      ],
      "outputs": [],
      "properties": {
        "cnr_id": "comfy-core",
        "ver": "0.3.28",
        "Node name for S&R": "PreviewAudio"
      },
      "widgets_values": [
        ""
      ]
    }
  ],
  "links": [
    [
      1,
      2,
      0,
      1,
      0,
      "AUDIO"
    ],
    [
      3,
      2,
      0,
      4,
      0,
      "AUDIO"
    ],
    [
      4,
      4,
      0,
      5,
      0,
      "*"
    ],
    [
      5,
      4,
      0,
      1,
      1,
      "STRING"
    ],
    [
      6,
      1,
      0,
      6,
      0,
      "AUDIO"
    ],
    [
      7,
      2,
      0,
      7,
      0,
      "AUDIO"
    ]
  ],
  "groups": [],
  "config": {},
  "extra": {
    "ds": {
      "scale": 1,
      "offset": [
        920.393392208884,
        -77.07916672626055
      ]
    },
    "VHS_latentpreview": false,
    "VHS_latentpreviewrate": 0,
    "VHS_MetadataImage": true,
    "VHS_KeepIntermediate": true
  },
  "version": 0.4
}